candle_pyo3-0.2.1.dist-info/METADATA
candle_pyo3-0.2.1.dist-info/WHEEL
candle/__init__.py
candle/candle.cpython-310-darwin.so
candle_pyo3-0.2.1.dist-info/RECORD
