Metadata-Version: 2.1
Name: candle-pyo3
Version: 0.2.1
Summary: Minimalist ML framework.
Keywords: blas,tensor,machine-learning
License: MIT OR Apache-2.0
Project-URL: Source Code, https://github.com/huggingface/candle
